zeff/__init__.py
zeff/plots.mplstyle
zeff/zeff.py
zeff-1.0.1.dist-info/LICENSE.txt
zeff-1.0.1.dist-info/METADATA
zeff-1.0.1.dist-info/WHEEL
zeff-1.0.1.dist-info/top_level.txt
zeff-1.0.1.dist-info/RECORD
