Metadata-Version: 2.1
Name: zeff
Version: 1.0.1
Summary: An effective nuclear charge calculator
Home-page: https://github.com/chicolucio/zeff/
Author: Francisco Bustamante
Author-email: 23560423+chicolucio@users.noreply.github.com
License: MIT
Project-URL: Documentation, https://zeff.readthedocs.io/en/latest/?badge=latest
Project-URL: Source, https://github.com/chicolucio/zeff/
Project-URL: Tracker, https://github.com/chicolucio/zeff/issues
Project-URL: Download, https://pypi.org/project/zeff
Keywords: effective nuclear charge,effective nuclear charge calculator,chemistry
Platform: any
Classifier: Development Status :: 4 - Beta
Classifier: Programming Language :: Python
Classifier: Programming Language :: Python :: 3
Classifier: Operating System :: OS Independent
Classifier: License :: OSI Approved :: MIT License
Classifier: Natural Language :: English
Classifier: Intended Audience :: Science/Research
Classifier: Topic :: Scientific/Engineering
Classifier: Topic :: Scientific/Engineering :: Chemistry
Requires-Python: >=3.10
License-File: LICENSE.txt
Requires-Dist: matplotlib ==3.8.2
Requires-Dist: mendeleev ==0.15.0
Requires-Dist: numpy ==1.26.4
Requires-Dist: pandas ==2.2.0
Requires-Dist: importlib-metadata ; python_version < "3.8"
Provides-Extra: testing
Requires-Dist: setuptools ; extra == 'testing'
Requires-Dist: pytest ; extra == 'testing'
Requires-Dist: pytest-cov ; extra == 'testing'
